[{"region":"Москва и Московская обл.","city":"Москва","number":53},{"region":"Москва и Московская обл.","city":"Абрамцево","number":79},{"region":"Москва и Московская обл.","city":"Алабино","number":5},{"region":"Москва и Московская обл.","city":"Апрелевка","number":28},{"region":"Москва и Московская обл.","city":"Архангельское","number":75},{"region":"Москва и Московская обл.","city":"Ашитково","number":72},{"region":"Москва и Московская обл.","city":"Байконур","number":36},{"region":"Москва и Московская обл.","city":"Бакшеево","number":16},{"region":"Москва и Московская обл.","city":"Балашиха","number":95},{"region":"Москва и Московская обл.","city":"Барыбино","number":61},{"region":"Москва и Московская обл.","city":"Белоомут","number":93},{"region":"Москва и Московская обл.","city":"Белые Столбы","number":55},{"region":"Москва и Московская обл.","city":"Бородино","number":97},{"region":"Москва и Московская обл.","city":"Бронницы","number":1},{"region":"Москва и Московская обл.","city":"Быково","number":98},{"region":"Москва и Московская обл.","city":"Валуево","number":1},{"region":"Москва и Московская обл.","city":"Вербилки","number":49},{"region":"Москва и Московская обл.","city":"Верея","number":67},{"region":"Москва и Московская обл.","city":"Видное","number":74},{"region":"Москва и Московская обл.","city":"Внуково","number":21},{"region":"Москва и Московская обл.","city":"Вождь Пролетариата","number":42},{"region":"Москва и Московская обл.","city":"Волоколамск","number":56},{"region":"Москва и Московская обл.","city":"Вороново","number":65},{"region":"Москва и Московская обл.","city":"Воскресенск","number":23},{"region":"Москва и Московская обл.","city":"Восточный","number":42},{"region":"Москва и Московская обл.","city":"Востряково","number":67},{"region":"Москва и Московская обл.","city":"Высоковск","number":60},{"region":"Москва и Московская обл.","city":"Голицино","number":20},{"region":"Москва и Московская обл.","city":"Деденево","number":96},{"region":"Москва и Московская обл.","city":"Дедовск","number":33},{"region":"Москва и Московская обл.","city":"Джержинский","number":65},{"region":"Москва и Московская обл.","city":"Дмитров","number":34},{"region":"Москва и Московская обл.","city":"Долгопрудный","number":28},{"region":"Москва и Московская обл.","city":"Домодедово","number":37},{"region":"Москва и Московская обл.","city":"Дорохово","number":77},{"region":"Москва и Московская обл.","city":"Дрезна","number":6},{"region":"Москва и Московская обл.","city":"Дубки","number":28},{"region":"Москва и Московская обл.","city":"Дубна","number":20},{"region":"Москва и Московская обл.","city":"Егорьевск","number":6},{"region":"Москва и Московская обл.","city":"Железнодорожный","number":51},{"region":"Москва и Московская обл.","city":"Жилево","number":39},{"region":"Москва и Московская обл.","city":"Жуковский","number":44},{"region":"Москва и Московская обл.","city":"Загорск","number":43},{"region":"Москва и Московская обл.","city":"Загорянский","number":98},{"region":"Москва и Московская обл.","city":"Запрудная","number":48},{"region":"Москва и Московская обл.","city":"Зарайск","number":22},{"region":"Москва и Московская обл.","city":"Звенигород","number":29},{"region":"Москва и Московская обл.","city":"Зеленоград","number":43},{"region":"Москва и Московская обл.","city":"Ивантеевка","number":63},{"region":"Москва и Московская обл.","city":"Икша","number":99},{"region":"Москва и Московская обл.","city":"Ильинский","number":50},{"region":"Москва и Московская обл.","city":"Истра","number":32},{"region":"Москва и Московская обл.","city":"Калининград","number":89},{"region":"Москва и Московская обл.","city":"Кашира","number":68},{"region":"Москва и Московская обл.","city":"Керва","number":22},{"region":"Москва и Московская обл.","city":"Климовск","number":12},{"region":"Москва и Московская обл.","city":"Клин","number":76},{"region":"Москва и Московская обл.","city":"Клязьма","number":66},{"region":"Москва и Московская обл.","city":"Кожино","number":82},{"region":"Москва и Московская обл.","city":"Кокошкино","number":37},{"region":"Москва и Московская обл.","city":"Коломна","number":30},{"region":"Москва и Московская обл.","city":"Колюбакино","number":58},{"region":"Москва и Московская обл.","city":"Королев","number":58},{"region":"Москва и Московская обл.","city":"Косино","number":98},{"region":"Москва и Московская обл.","city":"Котельники","number":82},{"region":"Москва и Московская обл.","city":"Красково","number":5},{"region":"Москва и Московская обл.","city":"Красноармейск","number":5},{"region":"Москва и Московская обл.","city":"Красногорск","number":49},{"region":"Москва и Московская обл.","city":"Краснозаводск","number":64},{"region":"Москва и Московская обл.","city":"Краснознаменск","number":50},{"region":"Москва и Московская обл.","city":"Красный Ткач","number":34},{"region":"Москва и Московская обл.","city":"Крюково","number":72},{"region":"Москва и Московская обл.","city":"Кубинка","number":93},{"region":"Москва и Московская обл.","city":"Купавна","number":87},{"region":"Москва и Московская обл.","city":"Куровское","number":45},{"region":"Москва и Московская обл.","city":"Лесной Городок","number":21},{"region":"Москва и Московская обл.","city":"Ликино-Дулево","number":82},{"region":"Москва и Московская обл.","city":"Лобня","number":57},{"region":"Москва и Московская обл.","city":"Лопатинский","number":61},{"region":"Москва и Московская обл.","city":"Лосино-Петровский","number":54},{"region":"Москва и Московская обл.","city":"Лотошино","number":35},{"region":"Москва и Московская обл.","city":"Лукино","number":86},{"region":"Москва и Московская обл.","city":"Луховицы","number":7},{"region":"Москва и Московская обл.","city":"Лыткарино","number":74},{"region":"Москва и Московская обл.","city":"Львовский","number":85},{"region":"Москва и Московская обл.","city":"Люберцы","number":6},{"region":"Москва и Московская обл.","city":"Малаховка","number":64},{"region":"Москва и Московская обл.","city":"Михайловское","number":91},{"region":"Москва и Московская обл.","city":"Михнево","number":12},{"region":"Москва и Московская обл.","city":"Можайск","number":68},{"region":"Москва и Московская обл.","city":"Монино","number":17},{"region":"Москва и Московская обл.","city":"Муханово","number":15},{"region":"Москва и Московская обл.","city":"Мытищи","number":53},{"region":"Москва и Московская обл.","city":"Нарофоминск","number":81},{"region":"Москва и Московская обл.","city":"Нахабино","number":51},{"region":"Москва и Московская обл.","city":"Некрасовка","number":79},{"region":"Москва и Московская обл.","city":"Немчиновка","number":59},{"region":"Москва и Московская обл.","city":"Новобратцевский","number":13},{"region":"Москва и Московская обл.","city":"Новоподрезково","number":69},{"region":"Москва и Московская обл.","city":"Ногинск","number":86},{"region":"Москва и Московская обл.","city":"Обухово","number":94},{"region":"Москва и Московская обл.","city":"Одинцово","number":35},{"region":"Москва и Московская обл.","city":"Ожерелье","number":64},{"region":"Москва и Московская обл.","city":"Озеры","number":65},{"region":"Москва и Московская обл.","city":"Октябрьский","number":20},{"region":"Москва и Московская обл.","city":"Опалиха","number":86},{"region":"Москва и Московская обл.","city":"Орехово-Зуево","number":17},{"region":"Москва и Московская обл.","city":"Павловский Посад","number":95},{"region":"Москва и Московская обл.","city":"Первомайский","number":24},{"region":"Москва и Московская обл.","city":"Пески","number":41},{"region":"Москва и Московская обл.","city":"Пироговский","number":65},{"region":"Москва и Московская обл.","city":"Подольск","number":72},{"region":"Москва и Московская обл.","city":"Полушкино","number":56},{"region":"Москва и Московская обл.","city":"Правдинский","number":17},{"region":"Москва и Московская обл.","city":"Привокзальный","number":39},{"region":"Москва и Московская обл.","city":"Пролетарский","number":85},{"region":"Москва и Московская обл.","city":"Протвино","number":82},{"region":"Москва и Московская обл.","city":"Пушкино","number":19},{"region":"Москва и Московская обл.","city":"Пущино","number":87},{"region":"Москва и Московская обл.","city":"Радовицкий","number":8},{"region":"Москва и Московская обл.","city":"Раменское","number":9},{"region":"Москва и Московская обл.","city":"Реутов","number":52},{"region":"Москва и Московская обл.","city":"Решетниково","number":48},{"region":"Москва и Московская обл.","city":"Родники","number":36},{"region":"Москва и Московская обл.","city":"Рошаль","number":61},{"region":"Москва и Московская обл.","city":"Рублево","number":34},{"region":"Москва и Московская обл.","city":"Руза","number":64},{"region":"Москва и Московская обл.","city":"Салтыковка","number":14},{"region":"Москва и Московская обл.","city":"Северный","number":13},{"region":"Москва и Московская обл.","city":"Сергиев Посад","number":1},{"region":"Москва и Московская обл.","city":"Серебряные Пруды","number":70},{"region":"Москва и Московская обл.","city":"Серпухов","number":69},{"region":"Москва и Московская обл.","city":"Солнечногорск","number":37},{"region":"Москва и Московская обл.","city":"Солнцево","number":3},{"region":"Москва и Московская обл.","city":"Софрино","number":5},{"region":"Москва и Московская обл.","city":"Старая Купавна","number":17},{"region":"Москва и Московская обл.","city":"Старбеево","number":88},{"region":"Москва и Московская обл.","city":"Ступино","number":25},{"region":"Москва и Московская обл.","city":"Сходня","number":32},{"region":"Москва и Московская обл.","city":"Талдом","number":87},{"region":"Москва и Московская обл.","city":"Текстильщик","number":95},{"region":"Москва и Московская обл.","city":"Темпы","number":17},{"region":"Москва и Московская обл.","city":"Тишково","number":12},{"region":"Москва и Московская обл.","city":"Томилино","number":4},{"region":"Москва и Московская обл.","city":"Троицк","number":22},{"region":"Москва и Московская обл.","city":"Туголесский Бор","number":23},{"region":"Москва и Московская обл.","city":"Тучково","number":16},{"region":"Москва и Московская обл.","city":"Уваровка","number":92},{"region":"Москва и Московская обл.","city":"Удельная","number":64},{"region":"Москва и Московская обл.","city":"Успенское","number":25},{"region":"Москва и Московская обл.","city":"Фирсановка","number":31},{"region":"Москва и Московская обл.","city":"Фосфоритный","number":36},{"region":"Москва и Московская обл.","city":"Фрязино","number":86},{"region":"Москва и Московская обл.","city":"Фряново","number":82},{"region":"Москва и Московская обл.","city":"Химки","number":97},{"region":"Москва и Московская обл.","city":"Хорлово","number":11},{"region":"Москва и Московская обл.","city":"Хотьково","number":23},{"region":"Москва и Московская обл.","city":"Черкизово","number":68},{"region":"Москва и Московская обл.","city":"Черноголовка","number":21},{"region":"Москва и Московская обл.","city":"Черусти","number":57},{"region":"Москва и Московская обл.","city":"Чехов","number":74},{"region":"Москва и Московская обл.","city":"Шарапово","number":29},{"region":"Москва и Московская обл.","city":"Шатура","number":12},{"region":"Москва и Московская обл.","city":"Шатурторф","number":7},{"region":"Москва и Московская обл.","city":"Шаховская","number":52},{"region":"Москва и Московская обл.","city":"Шереметьевский","number":75},{"region":"Москва и Московская обл.","city":"Щелково","number":27},{"region":"Москва и Московская обл.","city":"Щербинка","number":23},{"region":"Москва и Московская обл.","city":"Электрогорск","number":61},{"region":"Москва и Московская обл.","city":"Электросталь","number":59},{"region":"Москва и Московская обл.","city":"Электроугли","number":41},{"region":"Москва и Московская обл.","city":"Яхрома","number":81}]